quack_cli/main.py
quack_cli-0.2.1.dist-info/entry_points.txt
quack_cli-0.2.1.dist-info/WHEEL
quack_cli-0.2.1.dist-info/METADATA
quack_cli-0.2.1.dist-info/RECORD
